{
  "strategy": "large_cap_momentum",
  "defaults": {
    "lookback": 252,
    "skip_recent": 21,
    "top_pct": 10,
    "large_cap_pct": 50,
    "rebalance_freq": "M"
  },
  "sweep_1d": {
    "lookback": [
      {
        "param_value": 63,
        "default_value": 252,
        "sharpe_ratio": 0.733774,
        "total_return": 1.632415,
        "cagr": 0.274069,
        "max_drawdown": -0.913787,
        "calmar_ratio": 0.299926,
        "volatility": 0.991894,
        "sortino_ratio": 0.913083,
        "win_rate": 0.52973,
        "profit_factor": 1.154208,
        "avg_turnover": 0.005696
      },
      {
        "param_value": 126,
        "default_value": 252,
        "sharpe_ratio": 0.790251,
        "total_return": 2.64813,
        "cagr": 0.382474,
        "max_drawdown": -0.74143,
        "calmar_ratio": 0.51586,
        "volatility": 0.697739,
        "sortino_ratio": 0.961971,
        "win_rate": 0.538908,
        "profit_factor": 1.171254,
        "avg_turnover": 0.004638
      },
      {
        "param_value": 189,
        "default_value": 252,
        "sharpe_ratio": 0.877796,
        "total_return": 2.894784,
        "cagr": 0.405295,
        "max_drawdown": -0.575575,
        "calmar_ratio": 0.704156,
        "volatility": 0.521648,
        "sortino_ratio": 1.031198,
        "win_rate": 0.541457,
        "profit_factor": 1.201258,
        "avg_turnover": 0.003952
      },
      {
        "param_value": 252,
        "default_value": 252,
        "sharpe_ratio": 0.899987,
        "total_return": 2.451193,
        "cagr": 0.363408,
        "max_drawdown": -0.451902,
        "calmar_ratio": 0.804175,
        "volatility": 0.422178,
        "sortino_ratio": 1.020415,
        "win_rate": 0.556463,
        "profit_factor": 1.215209,
        "avg_turnover": 0.003493
      },
      {
        "param_value": 315,
        "default_value": 252,
        "sharpe_ratio": 1.029406,
        "total_return": 2.460728,
        "cagr": 0.36435,
        "max_drawdown": -0.372568,
        "calmar_ratio": 0.977941,
        "volatility": 0.338487,
        "sortino_ratio": 1.134239,
        "win_rate": 0.572065,
        "profit_factor": 1.259272,
        "avg_turnover": 0.002919
      }
    ],
    "skip_recent": [
      {
        "param_value": 0,
        "default_value": 21,
        "sharpe_ratio": 0.889399,
        "total_return": 2.210433,
        "cagr": 0.338957,
        "max_drawdown": -0.431104,
        "calmar_ratio": 0.786254,
        "volatility": 0.393642,
        "sortino_ratio": 1.007887,
        "win_rate": 0.548299,
        "profit_factor": 1.212612,
        "avg_turnover": 0.003357
      },
      {
        "param_value": 5,
        "default_value": 21,
        "sharpe_ratio": 0.949195,
        "total_return": 2.539786,
        "cagr": 0.372083,
        "max_drawdown": -0.422914,
        "calmar_ratio": 0.879809,
        "volatility": 0.395255,
        "sortino_ratio": 1.080179,
        "win_rate": 0.553741,
        "profit_factor": 1.227745,
        "avg_turnover": 0.003333
      },
      {
        "param_value": 10,
        "default_value": 21,
        "sharpe_ratio": 0.931021,
        "total_return": 2.524484,
        "cagr": 0.370597,
        "max_drawdown": -0.438656,
        "calmar_ratio": 0.844847,
        "volatility": 0.40691,
        "sortino_ratio": 1.055875,
        "win_rate": 0.552381,
        "profit_factor": 1.22304,
        "avg_turnover": 0.003396
      },
      {
        "param_value": 21,
        "default_value": 21,
        "sharpe_ratio": 0.899987,
        "total_return": 2.451193,
        "cagr": 0.363408,
        "max_drawdown": -0.451902,
        "calmar_ratio": 0.804175,
        "volatility": 0.422178,
        "sortino_ratio": 1.020415,
        "win_rate": 0.556463,
        "profit_factor": 1.215209,
        "avg_turnover": 0.003493
      },
      {
        "param_value": 42,
        "default_value": 21,
        "sharpe_ratio": 0.892389,
        "total_return": 2.466618,
        "cagr": 0.364931,
        "max_drawdown": -0.456952,
        "calmar_ratio": 0.798618,
        "volatility": 0.431508,
        "sortino_ratio": 1.017213,
        "win_rate": 0.556463,
        "profit_factor": 1.213003,
        "avg_turnover": 0.003635
      }
    ],
    "top_pct": [
      {
        "param_value": 5,
        "default_value": 10,
        "sharpe_ratio": 0.911063,
        "total_return": 3.322586,
        "cagr": 0.442427,
        "max_drawdown": -0.580606,
        "calmar_ratio": 0.762009,
        "volatility": 0.546296,
        "sortino_ratio": 1.028867,
        "win_rate": 0.552381,
        "profit_factor": 1.214518,
        "avg_turnover": 0.00401
      },
      {
        "param_value": 10,
        "default_value": 10,
        "sharpe_ratio": 0.899987,
        "total_return": 2.451193,
        "cagr": 0.363408,
        "max_drawdown": -0.451902,
        "calmar_ratio": 0.804175,
        "volatility": 0.422178,
        "sortino_ratio": 1.020415,
        "win_rate": 0.556463,
        "profit_factor": 1.215209,
        "avg_turnover": 0.003493
      },
      {
        "param_value": 15,
        "default_value": 10,
        "sharpe_ratio": 0.892953,
        "total_return": 1.993158,
        "cagr": 0.315681,
        "max_drawdown": -0.404036,
        "calmar_ratio": 0.78132,
        "volatility": 0.356576,
        "sortino_ratio": 1.015543,
        "win_rate": 0.545578,
        "profit_factor": 1.216319,
        "avg_turnover": 0.002933
      },
      {
        "param_value": 20,
        "default_value": 10,
        "sharpe_ratio": 0.869713,
        "total_return": 1.722073,
        "cagr": 0.284792,
        "max_drawdown": -0.393191,
        "calmar_ratio": 0.72431,
        "volatility": 0.327049,
        "sortino_ratio": 0.986056,
        "win_rate": 0.54966,
        "profit_factor": 1.211957,
        "avg_turnover": 0.002625
      },
      {
        "param_value": 30,
        "default_value": 10,
        "sharpe_ratio": 0.813327,
        "total_return": 1.264439,
        "cagr": 0.226954,
        "max_drawdown": -0.340051,
        "calmar_ratio": 0.667412,
        "volatility": 0.272944,
        "sortino_ratio": 0.921339,
        "win_rate": 0.546939,
        "profit_factor": 1.201367,
        "avg_turnover": 0.00207
      }
    ],
    "large_cap_pct": [
      {
        "param_value": 30,
        "default_value": 50,
        "sharpe_ratio": 0.853803,
        "total_return": 2.406145,
        "cagr": 0.358933,
        "max_drawdown": -0.50616,
        "calmar_ratio": 0.709129,
        "volatility": 0.461977,
        "sortino_ratio": 0.982732,
        "win_rate": 0.544218,
        "profit_factor": 1.201627,
        "avg_turnover": 0.003676
      },
      {
        "param_value": 40,
        "default_value": 50,
        "sharpe_ratio": 0.965828,
        "total_return": 2.872661,
        "cagr": 0.403293,
        "max_drawdown": -0.459256,
        "calmar_ratio": 0.878144,
        "volatility": 0.424087,
        "sortino_ratio": 1.101381,
        "win_rate": 0.563265,
        "profit_factor": 1.231364,
        "avg_turnover": 0.003426
      },
      {
        "param_value": 50,
        "default_value": 50,
        "sharpe_ratio": 0.899987,
        "total_return": 2.451193,
        "cagr": 0.363408,
        "max_drawdown": -0.451902,
        "calmar_ratio": 0.804175,
        "volatility": 0.422178,
        "sortino_ratio": 1.020415,
        "win_rate": 0.556463,
        "profit_factor": 1.215209,
        "avg_turnover": 0.003493
      },
      {
        "param_value": 70,
        "default_value": 50,
        "sharpe_ratio": 0.918859,
        "total_return": 2.504411,
        "cagr": 0.368639,
        "max_drawdown": -0.42803,
        "calmar_ratio": 0.861247,
        "volatility": 0.413712,
        "sortino_ratio": 1.051349,
        "win_rate": 0.55102,
        "profit_factor": 1.219724,
        "avg_turnover": 0.0035
      },
      {
        "param_value": 100,
        "default_value": 50,
        "sharpe_ratio": 0.930952,
        "total_return": 2.331861,
        "cagr": 0.351455,
        "max_drawdown": -0.395733,
        "calmar_ratio": 0.888111,
        "volatility": 0.380409,
        "sortino_ratio": 1.063011,
        "win_rate": 0.563265,
        "profit_factor": 1.222334,
        "avg_turnover": 0.003176
      }
    ]
  },
  "heatmap_2d": {
    "param_1": "lookback",
    "param_2": "top_pct",
    "values_1": [
      63,
      126,
      189,
      252,
      315
    ],
    "values_2": [
      5,
      10,
      15,
      20,
      30
    ],
    "grid": [
      {
        "lookback": 63,
        "top_pct": 5,
        "sharpe_ratio": 0.837035,
        "total_return": 1.745291,
        "cagr": 0.287526,
        "max_drawdown": -0.947989,
        "calmar_ratio": 0.303301,
        "volatility": 1.255845,
        "sortino_ratio": 1.050202,
        "win_rate": 0.539459,
        "profit_factor": 1.174382,
        "avg_turnover": 0.007601
      },
      {
        "lookback": 63,
        "top_pct": 10,
        "sharpe_ratio": 0.733774,
        "total_return": 1.632415,
        "cagr": 0.274069,
        "max_drawdown": -0.913787,
        "calmar_ratio": 0.299926,
        "volatility": 0.991894,
        "sortino_ratio": 0.913083,
        "win_rate": 0.52973,
        "profit_factor": 1.154208,
        "avg_turnover": 0.005696
      },
      {
        "lookback": 63,
        "top_pct": 15,
        "sharpe_ratio": 0.700389,
        "total_return": 1.781079,
        "cagr": 0.291706,
        "max_drawdown": -0.838152,
        "calmar_ratio": 0.348034,
        "volatility": 0.781785,
        "sortino_ratio": 0.870521,
        "win_rate": 0.540541,
        "profit_factor": 1.147856,
        "avg_turnover": 0.004159
      },
      {
        "lookback": 63,
        "top_pct": 20,
        "sharpe_ratio": 0.711201,
        "total_return": 1.911777,
        "cagr": 0.306636,
        "max_drawdown": -0.753844,
        "calmar_ratio": 0.406764,
        "volatility": 0.642892,
        "sortino_ratio": 0.882561,
        "win_rate": 0.539459,
        "profit_factor": 1.151389,
        "avg_turnover": 0.003357
      },
      {
        "lookback": 63,
        "top_pct": 30,
        "sharpe_ratio": 0.696253,
        "total_return": 1.567124,
        "cagr": 0.266086,
        "max_drawdown": -0.615503,
        "calmar_ratio": 0.432307,
        "volatility": 0.471052,
        "sortino_ratio": 0.865559,
        "win_rate": 0.534054,
        "profit_factor": 1.150101,
        "avg_turnover": 0.00234
      },
      {
        "lookback": 126,
        "top_pct": 5,
        "sharpe_ratio": 0.765675,
        "total_return": 2.235824,
        "cagr": 0.341599,
        "max_drawdown": -0.844552,
        "calmar_ratio": 0.404474,
        "volatility": 0.907719,
        "sortino_ratio": 0.94512,
        "win_rate": 0.536585,
        "profit_factor": 1.162709,
        "avg_turnover": 0.005767
      },
      {
        "lookback": 126,
        "top_pct": 10,
        "sharpe_ratio": 0.790251,
        "total_return": 2.64813,
        "cagr": 0.382474,
        "max_drawdown": -0.74143,
        "calmar_ratio": 0.51586,
        "volatility": 0.697739,
        "sortino_ratio": 0.961971,
        "win_rate": 0.538908,
        "profit_factor": 1.171254,
        "avg_turnover": 0.004638
      },
      {
        "lookback": 126,
        "top_pct": 15,
        "sharpe_ratio": 0.770994,
        "total_return": 2.24597,
        "cagr": 0.342651,
        "max_drawdown": -0.669422,
        "calmar_ratio": 0.511861,
        "volatility": 0.56911,
        "sortino_ratio": 0.933392,
        "win_rate": 0.536585,
        "profit_factor": 1.168875,
        "avg_turnover": 0.003659
      },
      {
        "lookback": 126,
        "top_pct": 20,
        "sharpe_ratio": 0.736648,
        "total_return": 1.870595,
        "cagr": 0.301987,
        "max_drawdown": -0.627735,
        "calmar_ratio": 0.481074,
        "volatility": 0.508962,
        "sortino_ratio": 0.890157,
        "win_rate": 0.54007,
        "profit_factor": 1.162343,
        "avg_turnover": 0.003057
      },
      {
        "lookback": 126,
        "top_pct": 30,
        "sharpe_ratio": 0.688403,
        "total_return": 1.38128,
        "cagr": 0.242499,
        "max_drawdown": -0.552813,
        "calmar_ratio": 0.438664,
        "volatility": 0.408724,
        "sortino_ratio": 0.83343,
        "win_rate": 0.536585,
        "profit_factor": 1.153903,
        "avg_turnover": 0.002247
      },
      {
        "lookback": 189,
        "top_pct": 5,
        "sharpe_ratio": 0.811687,
        "total_return": 2.811817,
        "cagr": 0.397743,
        "max_drawdown": -0.697758,
        "calmar_ratio": 0.570029,
        "volatility": 0.662045,
        "sortino_ratio": 0.954812,
        "win_rate": 0.541457,
        "profit_factor": 1.183608,
        "avg_turnover": 0.004583
      },
      {
        "lookback": 189,
        "top_pct": 10,
        "sharpe_ratio": 0.877796,
        "total_return": 2.894784,
        "cagr": 0.405295,
        "max_drawdown": -0.575575,
        "calmar_ratio": 0.704156,
        "volatility": 0.521648,
        "sortino_ratio": 1.031198,
        "win_rate": 0.541457,
        "profit_factor": 1.201258,
        "avg_turnover": 0.003952
      },
      {
        "lookback": 189,
        "top_pct": 15,
        "sharpe_ratio": 0.813676,
        "total_return": 2.141462,
        "cagr": 0.3317,
        "max_drawdown": -0.530715,
        "calmar_ratio": 0.625006,
        "volatility": 0.456944,
        "sortino_ratio": 0.958409,
        "win_rate": 0.541457,
        "profit_factor": 1.187233,
        "avg_turnover": 0.003326
      },
      {
        "lookback": 189,
        "top_pct": 20,
        "sharpe_ratio": 0.811596,
        "total_return": 1.856141,
        "cagr": 0.300343,
        "max_drawdown": -0.46823,
        "calmar_ratio": 0.641444,
        "volatility": 0.396758,
        "sortino_ratio": 0.950104,
        "win_rate": 0.547739,
        "profit_factor": 1.188176,
        "avg_turnover": 0.002796
      },
      {
        "lookback": 189,
        "top_pct": 30,
        "sharpe_ratio": 0.77532,
        "total_return": 1.406405,
        "cagr": 0.245767,
        "max_drawdown": -0.422756,
        "calmar_ratio": 0.581345,
        "volatility": 0.327199,
        "sortino_ratio": 0.899731,
        "win_rate": 0.54397,
        "profit_factor": 1.183005,
        "avg_turnover": 0.002156
      },
      {
        "lookback": 252,
        "top_pct": 5,
        "sharpe_ratio": 0.911063,
        "total_return": 3.322586,
        "cagr": 0.442427,
        "max_drawdown": -0.580606,
        "calmar_ratio": 0.762009,
        "volatility": 0.546296,
        "sortino_ratio": 1.028867,
        "win_rate": 0.552381,
        "profit_factor": 1.214518,
        "avg_turnover": 0.00401
      },
      {
        "lookback": 252,
        "top_pct": 10,
        "sharpe_ratio": 0.899987,
        "total_return": 2.451193,
        "cagr": 0.363408,
        "max_drawdown": -0.451902,
        "calmar_ratio": 0.804175,
        "volatility": 0.422178,
        "sortino_ratio": 1.020415,
        "win_rate": 0.556463,
        "profit_factor": 1.215209,
        "avg_turnover": 0.003493
      },
      {
        "lookback": 252,
        "top_pct": 15,
        "sharpe_ratio": 0.892953,
        "total_return": 1.993158,
        "cagr": 0.315681,
        "max_drawdown": -0.404036,
        "calmar_ratio": 0.78132,
        "volatility": 0.356576,
        "sortino_ratio": 1.015543,
        "win_rate": 0.545578,
        "profit_factor": 1.216319,
        "avg_turnover": 0.002933
      },
      {
        "lookback": 252,
        "top_pct": 20,
        "sharpe_ratio": 0.869713,
        "total_return": 1.722073,
        "cagr": 0.284792,
        "max_drawdown": -0.393191,
        "calmar_ratio": 0.72431,
        "volatility": 0.327049,
        "sortino_ratio": 0.986056,
        "win_rate": 0.54966,
        "profit_factor": 1.211957,
        "avg_turnover": 0.002625
      },
      {
        "lookback": 252,
        "top_pct": 30,
        "sharpe_ratio": 0.813327,
        "total_return": 1.264439,
        "cagr": 0.226954,
        "max_drawdown": -0.340051,
        "calmar_ratio": 0.667412,
        "volatility": 0.272944,
        "sortino_ratio": 0.921339,
        "win_rate": 0.546939,
        "profit_factor": 1.201367,
        "avg_turnover": 0.00207
      },
      {
        "lookback": 315,
        "top_pct": 5,
        "sharpe_ratio": 1.110312,
        "total_return": 3.691515,
        "cagr": 0.472295,
        "max_drawdown": -0.469617,
        "calmar_ratio": 1.005704,
        "volatility": 0.405067,
        "sortino_ratio": 1.202865,
        "win_rate": 0.56315,
        "profit_factor": 1.280516,
        "avg_turnover": 0.003247
      },
      {
        "lookback": 315,
        "top_pct": 10,
        "sharpe_ratio": 1.029406,
        "total_return": 2.460728,
        "cagr": 0.36435,
        "max_drawdown": -0.372568,
        "calmar_ratio": 0.977941,
        "volatility": 0.338487,
        "sortino_ratio": 1.134239,
        "win_rate": 0.572065,
        "profit_factor": 1.259272,
        "avg_turnover": 0.002919
      },
      {
        "lookback": 315,
        "top_pct": 15,
        "sharpe_ratio": 0.944989,
        "total_return": 1.745695,
        "cagr": 0.287573,
        "max_drawdown": -0.334596,
        "calmar_ratio": 0.859464,
        "volatility": 0.291645,
        "sortino_ratio": 1.030832,
        "win_rate": 0.561664,
        "profit_factor": 1.241199,
        "avg_turnover": 0.002572
      },
      {
        "lookback": 315,
        "top_pct": 20,
        "sharpe_ratio": 0.902693,
        "total_return": 1.486727,
        "cagr": 0.256045,
        "max_drawdown": -0.31618,
        "calmar_ratio": 0.809808,
        "volatility": 0.271458,
        "sortino_ratio": 0.985781,
        "win_rate": 0.557207,
        "profit_factor": 1.23234,
        "avg_turnover": 0.002328
      },
      {
        "lookback": 315,
        "top_pct": 30,
        "sharpe_ratio": 0.885291,
        "total_return": 1.177174,
        "cagr": 0.214947,
        "max_drawdown": -0.279702,
        "calmar_ratio": 0.768483,
        "volatility": 0.226469,
        "sortino_ratio": 0.955527,
        "win_rate": 0.566122,
        "profit_factor": 1.232777,
        "avg_turnover": 0.001861
      }
    ]
  },
  "robustness": {
    "lookback": {
      "n_values_tested": 5,
      "sharpe_min": 0.734,
      "sharpe_max": 1.029,
      "sharpe_mean": 0.866,
      "sharpe_std": 0.101,
      "sharpe_range": 0.296,
      "coefficient_of_variation": 0.117,
      "best_value": 315,
      "best_sharpe": 1.029,
      "default_value": 252,
      "default_sharpe": 0.9,
      "all_positive_sharpe": true,
      "robustness": "ROBUST"
    },
    "skip_recent": {
      "n_values_tested": 5,
      "sharpe_min": 0.889,
      "sharpe_max": 0.949,
      "sharpe_mean": 0.912,
      "sharpe_std": 0.024,
      "sharpe_range": 0.06,
      "coefficient_of_variation": 0.026,
      "best_value": 5,
      "best_sharpe": 0.949,
      "default_value": 21,
      "default_sharpe": 0.9,
      "all_positive_sharpe": true,
      "robustness": "ROBUST"
    },
    "top_pct": {
      "n_values_tested": 5,
      "sharpe_min": 0.813,
      "sharpe_max": 0.911,
      "sharpe_mean": 0.877,
      "sharpe_std": 0.035,
      "sharpe_range": 0.098,
      "coefficient_of_variation": 0.04,
      "best_value": 5,
      "best_sharpe": 0.911,
      "default_value": 10,
      "default_sharpe": 0.9,
      "all_positive_sharpe": true,
      "robustness": "ROBUST"
    },
    "large_cap_pct": {
      "n_values_tested": 5,
      "sharpe_min": 0.854,
      "sharpe_max": 0.966,
      "sharpe_mean": 0.914,
      "sharpe_std": 0.037,
      "sharpe_range": 0.112,
      "coefficient_of_variation": 0.04,
      "best_value": 40,
      "best_sharpe": 0.966,
      "default_value": 50,
      "default_sharpe": 0.9,
      "all_positive_sharpe": true,
      "robustness": "ROBUST"
    }
  }
}